batata/PyDown.py
batata/__init__.py
batata/aliases.py
batata/apis.py
batata/cli.py
batata/colors.py
batata/dates.py
batata/errors.py
batata/files.py
batata/formas.py
batata/geral.py
batata/mat.py
batata/mcoptions.py
batata/scraping.py
batata_lib-0.1.8.dist-info/METADATA
batata_lib-0.1.8.dist-info/WHEEL
batata_lib-0.1.8.dist-info/top_level.txt
batata_lib-0.1.8.dist-info/RECORD
